smartex/__about__.py
smartex/__init__.py
smartex/__main__.py
smartex/smartex.py
smartex-0.0.1.dist-info/METADATA
smartex-0.0.1.dist-info/WHEEL
smartex-0.0.1.dist-info/licenses/LICENSE.txt
smartex-0.0.1.dist-info/RECORD
